Roundtrip/__init__.py
Roundtrip/__main__.py
Roundtrip/cli.py
Roundtrip/model.py
Roundtrip/roundtrip.py
Roundtrip/util.py
pyroundtrip/__init__.py
pyroundtrip/__main__.py
pyroundtrip/cli.py
pyroundtrip/model.py
pyroundtrip/roundtrip.py
pyroundtrip/util.py
pyroundtrip-2.0.1.dist-info/LICENSE
pyroundtrip-2.0.1.dist-info/METADATA
pyroundtrip-2.0.1.dist-info/WHEEL
pyroundtrip-2.0.1.dist-info/entry_points.txt
pyroundtrip-2.0.1.dist-info/top_level.txt
pyroundtrip-2.0.1.dist-info/RECORD
