Metadata-Version: 2.1
Name: pyroundtrip
Version: 2.0.1
Summary: Roundtrip: density estimation with deep generative neural networks
Home-page: https://github.com/kimmo1019/Roundtrip
Author: Qiao Liu
Author-email: liuqiao@stanford.edu
Classifier: Programming Language :: Python :: 3
Classifier: License :: OSI Approved :: MIT License
Classifier: Operating System :: OS Independent
Requires-Python: >=3.7
License-File: LICENSE
Requires-Dist: tensorflow (>=2.8.0)
Requires-Dist: scikit-learn
Requires-Dist: pandas
Requires-Dist: python-dateutil
